opencast_externalapi/__init__.py
opencast_externalapi/apiclient.py
opencast_externalapi/base.py
opencast_externalapi/events.py
opencast_externalapi/groups.py
opencast_externalapi/series.py
opencast_externalapi-0.0.1.dev5.dist-info/DESCRIPTION.rst
opencast_externalapi-0.0.1.dev5.dist-info/METADATA
opencast_externalapi-0.0.1.dev5.dist-info/RECORD
opencast_externalapi-0.0.1.dev5.dist-info/WHEEL
opencast_externalapi-0.0.1.dev5.dist-info/metadata.json
opencast_externalapi-0.0.1.dev5.dist-info/top_level.txt
