Metadata-Version: 2.0
Name: opencast-externalapi
Version: 0.0.1.dev5
Summary: A Python client for the Opencast external API
Home-page: https://zivgitlab.uni-muenster.de/electures/contrib/python-opencast-externalapi
Author: University of Münster, eLectures team
Author-email: electures.dev@uni-muenster.de
License: ECL-2.0
Keywords: api client development opencast externalapi
Platform: UNKNOWN
Classifier: Development Status :: 2 - Pre-Alpha
Classifier: Intended Audience :: Developers
Classifier: License :: OSI Approved :: Apache Software License
Classifier: Programming Language :: Python :: 3 :: Only
Classifier: Topic :: Software Development :: Libraries :: Python Modules
Requires-Dist: requests
